dblur/__init__.py
dblur/multi_modal_deblur.py
dblur/data/__init__.py
dblur/data/augment.py
dblur/data/dataset.py
dblur/data/inference_dataset.py
dblur/default/__init__.py
dblur/default/fnafnet.py
dblur/default/mscnn.py
dblur/default/nafnet.py
dblur/default/restormer.py
dblur/default/srn.py
dblur/default/stack_dmphn.py
dblur/default/textdbn.py
dblur/losses/__init__.py
dblur/losses/charbonnier_loss.py
dblur/losses/fnafnet.py
dblur/losses/frequency_reconstruction_loss.py
dblur/losses/mscnn.py
dblur/losses/psnr_loss.py
dblur/losses/srn.py
dblur/losses/stack_dmphn.py
dblur/models/__init__.py
dblur/models/fnafnet.py
dblur/models/mscnn.py
dblur/models/nafnet.py
dblur/models/restormer.py
dblur/models/srn.py
dblur/models/stack_dmphn.py
dblur/models/textdbn.py
dblur/schedulers/__init__.py
dblur/schedulers/mscnn.py
dblur/schedulers/textdbn.py
dblur/testers/__init__.py
dblur/testers/base_tester.py
dblur/testers/fnafnet.py
dblur/testers/mscnn.py
dblur/testers/nafnet.py
dblur/testers/restormer.py
dblur/testers/srn.py
dblur/testers/stack_dmphn.py
dblur/testers/textdbn.py
dblur/trainers/__init__.py
dblur/trainers/base_trainer.py
dblur/trainers/fnafnet.py
dblur/trainers/mscnn.py
dblur/trainers/nafnet.py
dblur/trainers/restormer.py
dblur/trainers/srn.py
dblur/trainers/stack_dmphn.py
dblur/trainers/textdbn.py
dblur/utils/__init__.py
dblur/utils/dataset_utils.py
dblur/utils/img_utils.py
dblur/utils/metrics.py
dblur-1.0.0.dist-info/LICENSE
dblur-1.0.0.dist-info/METADATA
dblur-1.0.0.dist-info/WHEEL
dblur-1.0.0.dist-info/top_level.txt
dblur-1.0.0.dist-info/RECORD
