Metadata-Version: 2.1
Name: dblur
Version: 1.0.0
Summary: An extensive, highly customisable python package for image deblurring
Home-page: https://github.com/Jishnu8/DBlur-An-Image-Deblurring-Toolkit
Author: Jishnu Parayil Shibu
Author-email: jishnu82003@gmail.com
Project-URL: Bug Tracker, https://github.com/Jishnu8/DBlur-An-Image-Deblurring-Toolkit/issues
Classifier: Programming Language :: Python :: 3
Classifier: License :: OSI Approved :: MIT License
Classifier: Operating System :: OS Independent
Requires-Python: >=3.6
License-File: LICENSE
Requires-Dist: scipy
Requires-Dist: numpy
Requires-Dist: torch
Requires-Dist: tensorboard
Requires-Dist: torchmetrics
Requires-Dist: piq
